stub_bot_core/__init__.py
stub_bot_core/module.py
stub_bot_core-0.0.1.dist-info/LICENSE
stub_bot_core-0.0.1.dist-info/METADATA
stub_bot_core-0.0.1.dist-info/WHEEL
stub_bot_core-0.0.1.dist-info/top_level.txt
stub_bot_core-0.0.1.dist-info/RECORD
